yapowf/__init__.py
yapowf/yapowf.py
yapowf/conn/__init__.py
yapowf/conn/conn.py
yapowf/events/__init__.py
yapowf/events/events.py
yapowf/params/__init__.py
yapowf/params/gridparams.py
yapowf/res/__init__.py
yapowf/res/dynsim.py
yapowf/res/ldf.py
yapowf/utils/__init__.py
yapowf-0.0.7.dist-info/LICENSE.txt
yapowf-0.0.7.dist-info/METADATA
yapowf-0.0.7.dist-info/WHEEL
yapowf-0.0.7.dist-info/top_level.txt
yapowf-0.0.7.dist-info/RECORD
