Metadata-Version: 2.1
Name: yapowf
Version: 0.0.7
Summary: A new Python Power Factory API
Home-page: UNKNOWN
Author: Camilo Romero
Author-email: camilo.romers@gmail.com
License: GNU GPLv3
Keywords: power factory api,digsilent python
Platform: UNKNOWN
Classifier: Development Status :: 1 - Planning
Classifier: Intended Audience :: Education
Classifier: Operating System :: Microsoft :: Windows :: Windows 10
Classifier: License :: OSI Approved :: GNU General Public License v3 or later (GPLv3+)
Classifier: Programming Language :: Python :: 3
Requires-Dist: pandas
